bonelate/__init__.py
bonelate/__main__.py
bonelate/parser.py
bonelate/renderer.py
bonelate/rule.py
bonelate/token.py
bonelate/utils.py
bonelate/plugins/__init__.py
bonelate/plugins/formula.py
bonelate/plugins/number.py
bonelate/plugins/plugin.py
Bonelate-0.1.2.dist-info/LICENSE
Bonelate-0.1.2.dist-info/METADATA
Bonelate-0.1.2.dist-info/WHEEL
Bonelate-0.1.2.dist-info/entry_points.txt
Bonelate-0.1.2.dist-info/top_level.txt
Bonelate-0.1.2.dist-info/RECORD
