Metadata-Version: 2.1
Name: Bonelate
Version: 0.1.2
Summary: Bonelate 是一个基于 pyparsing 针对 LaTeX 的 mustache 模版语言变种的实现。
Home-page: https://gitee.com/zrr1999/bonetex
Author: 六个骨头
Author-email: 2742392377@qq.com
License: UNKNOWN
Platform: any
Classifier: Programming Language :: Python :: 3
Classifier: License :: OSI Approved :: MIT License
Classifier: Operating System :: OS Independent
Requires-Dist: pyparsing
Requires-Dist: sympy
Provides-Extra: all
Requires-Dist: pytest ; extra == 'all'
Requires-Dist: yaml ; extra == 'all'
Requires-Dist: watchdog ; extra == 'all'
Requires-Dist: typer ; extra == 'all'
Provides-Extra: command
Requires-Dist: watchdog ; extra == 'command'
Requires-Dist: typer ; extra == 'command'
Provides-Extra: test
Requires-Dist: pytest ; extra == 'test'
Requires-Dist: yaml ; extra == 'test'
